TheArtOfDataScience/README.md
TheArtOfDataScience/__init__.py
TheArtOfDataScience/__main__.py
TheArtOfDataScience/file.epub
TheArtOfDataScience/index.html
TheArtOfDataScience/css/__init__.py
TheArtOfDataScience/css/annotations.css
TheArtOfDataScience/css/main.css
TheArtOfDataScience/css/normalize.css
TheArtOfDataScience/css/popup.css
TheArtOfDataScience/font/__init__.py
TheArtOfDataScience/font/fontello.eot
TheArtOfDataScience/font/fontello.svg
TheArtOfDataScience/font/fontello.ttf
TheArtOfDataScience/font/fontello.woff
TheArtOfDataScience/img/__init__.py
TheArtOfDataScience/img/annotator-glyph-sprite.png
TheArtOfDataScience/img/annotator-icon-sprite.png
TheArtOfDataScience/img/apple-touch-icon.png
TheArtOfDataScience/img/cancelfullscreen.png
TheArtOfDataScience/img/close.png
TheArtOfDataScience/img/fullscreen.png
TheArtOfDataScience/img/loader.gif
TheArtOfDataScience/img/menu-icon.png
TheArtOfDataScience/img/save.png
TheArtOfDataScience/img/saved.png
TheArtOfDataScience/img/settings-s.png
TheArtOfDataScience/img/settings.png
TheArtOfDataScience/img/star.png
TheArtOfDataScience/js/__init__.py
TheArtOfDataScience/js/epub.js
TheArtOfDataScience/js/epub.min.js
TheArtOfDataScience/js/epub.min.map
TheArtOfDataScience/js/hooks.min.js
TheArtOfDataScience/js/hooks.min.map
TheArtOfDataScience/js/reader.js
TheArtOfDataScience/js/reader.js.map
TheArtOfDataScience/js/reader.min.js
TheArtOfDataScience/js/reader.min.map
TheArtOfDataScience/js/hooks/__init__.py
TheArtOfDataScience/js/hooks/extensions/__init__.py
TheArtOfDataScience/js/hooks/extensions/highlight.js
TheArtOfDataScience/js/libs/__init__.py
TheArtOfDataScience/js/libs/jquery.min.js
TheArtOfDataScience/js/libs/localforage.min.js
TheArtOfDataScience/js/libs/screenfull.js
TheArtOfDataScience/js/libs/screenfull.min.js
TheArtOfDataScience/js/libs/zip.min.js
TheArtOfDataScience/js/plugins/__init__.py
TheArtOfDataScience/js/plugins/hypothesis.js
TheArtOfDataScience/js/plugins/search.js
the_art_of_data_science-2024.3.2.0.dist-info/METADATA
the_art_of_data_science-2024.3.2.0.dist-info/WHEEL
the_art_of_data_science-2024.3.2.0.dist-info/entry_points.txt
the_art_of_data_science-2024.3.2.0.dist-info/top_level.txt
the_art_of_data_science-2024.3.2.0.dist-info/RECORD
